EmulsiPred/__init__.py
EmulsiPred/__main__.py
EmulsiPred/emulsipred.py
EmulsiPred/predictors.py
EmulsiPred/utils.py
EmulsiPred/NormalizationValues/a_norm.csv
EmulsiPred/NormalizationValues/b_norm.csv
EmulsiPred/NormalizationValues/g_norm.csv
EmulsiPred-0.0.3.dist-info/LICENSE
EmulsiPred-0.0.3.dist-info/METADATA
EmulsiPred-0.0.3.dist-info/WHEEL
EmulsiPred-0.0.3.dist-info/top_level.txt
EmulsiPred-0.0.3.dist-info/RECORD
