Metadata-Version: 2.1
Name: EmulsiPred
Version: 0.0.3
Summary: A package to predict emulsifying potential of peptides
Home-page: https://github.com/MarcatiliLab/EmulsiPred
Author: Paolo Marcatili, Tobias Olsen, Egon Hansen
Author-email: pamar@dtu.dk
Classifier: Development Status :: 4 - Beta
Classifier: Programming Language :: Python :: 3.9
Classifier: License :: OSI Approved :: MIT License
Classifier: Operating System :: OS Independent
Requires-Python: >=3.9
License-File: LICENSE
Requires-Dist: numpy
Requires-Dist: pandas
